Metadata-Version: 2.1
Name: geneticregression
Version: 0.1.4
Summary: Genetic Regression
Home-page: https://github.com/StephenMal/genetic_regression
Author: Stephen Maldonado
Author-email: genetic_regression@stephenmal.com
License: UNKNOWN
Platform: UNKNOWN
Classifier: Development Status :: 1 - Planning
Classifier: Programming Language :: Python :: 3 :: Only
Classifier: Topic :: Utilities
